LICENSE.txt
README.md
setup.cfg
setup.py
lamp_display/__init__.py
lamp_display.egg-info/PKG-INFO
lamp_display.egg-info/SOURCES.txt
lamp_display.egg-info/dependency_links.txt
lamp_display.egg-info/requires.txt
lamp_display.egg-info/top_level.txt