Metadata-Version: 2.1
Name: lamp-display
Version: 1.0
Summary: A Python module to simulate a Minecraft lamp display.
Home-page: https://github.com/Matthias1590/LampDisplay
Author: Matthias Wijnsma
Author-email: matthias.wijnsma@outlook.com
License: MIT
Download-URL: https://github.com/Matthias1590/LampDisplay/archive/refs/tags/v1.0.tar.gz
Platform: UNKNOWN
License-File: LICENSE.txt
